{"text": " There it is. Alright. Little girl's knife is cooking. The boy is getting her one, but the stool is going to fall off the stool. The mother is doing the dishes. Unfortunately, the sink is overflowing on the floor. Oh, that's his feet. I thought there was something on the other boy's foot, but it's just part of one foot on top of the other. Little girl, I don't know whether she's laughing or asking for the cookie or saying, Shhh, so mother doesn't hear me. Okay.", "segments": [{"id": 0, "seek": 0, "start": 0.0, "end": 2.0, "text": " There it is.", "tokens": [1318, 340, 318, 13], "temperature": 0.0, "avg_logprob": -0.44071590423583984, "compression_ratio": 1.382608695652174, "no_speech_prob": 0.3000222444534302}, {"id": 1, "seek": 0, "start": 3.0, "end": 5.0, "text": " Alright.", "tokens": [40967, 13], "temperature": 0.0, "avg_logprob": -0.44071590423583984, "compression_ratio": 1.382608695652174, "no_speech_prob": 0.3000222444534302}, {"id": 2, "seek": 0, "start": 6.0, "end": 9.0, "text": " Little girl's knife is cooking.", "tokens": [7703, 2576, 338, 9845, 318, 10801, 13], "temperature": 0.0, "avg_logprob": -0.44071590423583984, "compression_ratio": 1.382608695652174, "no_speech_prob": 0.3000222444534302}, {"id": 3, "seek": 0, "start": 9.0, "end": 16.0, "text": " The boy is getting her one, but the stool is going to fall off the stool.", "tokens": [383, 2933, 318, 1972, 607, 530, 11, 475, 262, 38753, 318, 1016, 284, 2121, 572, 262, 38753, 13], "temperature": 0.0, "avg_logprob": -0.44071590423583984, "compression_ratio": 1.382608695652174, "no_speech_prob": 0.3000222444534302}, {"id": 4, "seek": 0, "start": 20.0, "end": 24.0, "text": " The mother is doing the dishes.", "tokens": [383, 2802, 318, 1804, 262, 16759, 13], "temperature": 0.0, "avg_logprob": -0.44071590423583984, "compression_ratio": 1.382608695652174, "no_speech_prob": 0.3000222444534302}, {"id": 5, "seek": 2400, "start": 24.0, "end": 30.0, "text": " Unfortunately, the sink is overflowing on the floor.", "tokens": [8989, 11, 262, 14595, 318, 43347, 319, 262, 4314, 13], "temperature": 0.0, "avg_logprob": -0.3193070784859035, "compression_ratio": 1.0, "no_speech_prob": 0.00021315770572982728}, {"id": 6, "seek": 2400, "start": 46.0, "end": 48.0, "text": " Oh, that's his feet.", "tokens": [3966, 11, 326, 338, 465, 3625, 13], "temperature": 0.0, "avg_logprob": -0.3193070784859035, "compression_ratio": 1.0, "no_speech_prob": 0.00021315770572982728}, {"id": 7, "seek": 4800, "start": 48.0, "end": 60.0, "text": " I thought there was something on the other boy's foot, but it's just part of one foot on top of the other.", "tokens": [314, 1807, 612, 373, 1223, 319, 262, 584, 2933, 338, 2366, 11, 475, 340, 338, 655, 636, 286, 530, 2366, 319, 1353, 286, 262, 584, 13], "temperature": 0.0, "avg_logprob": -0.25825570121644037, "compression_ratio": 1.4736842105263157, "no_speech_prob": 0.00013763649621978402}, {"id": 8, "seek": 4800, "start": 62.0, "end": 70.0, "text": " Little girl, I don't know whether she's laughing or asking for the cookie or saying,", "tokens": [7703, 2576, 11, 314, 836, 470, 760, 1771, 673, 338, 14376, 393, 4737, 329, 262, 19751, 393, 2282, 11], "temperature": 0.0, "avg_logprob": -0.25825570121644037, "compression_ratio": 1.4736842105263157, "no_speech_prob": 0.00013763649621978402}, {"id": 9, "seek": 4800, "start": 70.0, "end": 72.0, "text": " Shhh, so mother doesn't hear me.", "tokens": [911, 12337, 11, 523, 2802, 1595, 470, 3285, 502, 13], "temperature": 0.0, "avg_logprob": -0.25825570121644037, "compression_ratio": 1.4736842105263157, "no_speech_prob": 0.00013763649621978402}, {"id": 10, "seek": 7200, "start": 72.0, "end": 74.0, "text": " Okay.", "tokens": [50363, 16805, 13, 50463], "temperature": 0.0, "avg_logprob": -0.6094540119171142, "compression_ratio": 0.38461538461538464, "no_speech_prob": 1.8448139371685102e-06}], "language": "en", "label": 1}