{"text": " and make her look a little more familiar to her lips. And that's about everything that's going to happen. Looking out the window, maybe it, I don't know if it's the breeze blowing the curtains, because the curtains look a little wee bit, over the, over the window blind, but the window looks a little wee bit puffy. So maybe there's a slight breeze coming in the, in the kitchen window. Mom is drying the dishes and she's forgetting herself, and the water is overflowing.", "segments": [{"id": 0, "seek": 0, "start": 0.0, "end": 4.0, "text": " and make her look a little more familiar to her lips.", "tokens": [290, 787, 607, 804, 257, 1310, 517, 5385, 284, 607, 11914, 13], "temperature": 0.0, "avg_logprob": -0.36820535098805146, "compression_ratio": 1.812206572769953, "no_speech_prob": 0.5888912677764893}, {"id": 1, "seek": 0, "start": 4.0, "end": 8.0, "text": " And that's about everything that's going to happen.", "tokens": [843, 326, 338, 546, 2279, 326, 338, 1016, 284, 1645, 13], "temperature": 0.0, "avg_logprob": -0.36820535098805146, "compression_ratio": 1.812206572769953, "no_speech_prob": 0.5888912677764893}, {"id": 2, "seek": 0, "start": 8.0, "end": 14.0, "text": " Looking out the window, maybe it, I don't know if it's the breeze blowing the curtains,", "tokens": [15616, 503, 262, 4324, 11, 3863, 340, 11, 314, 836, 470, 760, 611, 340, 338, 262, 28633, 19280, 262, 41160, 11], "temperature": 0.0, "avg_logprob": -0.36820535098805146, "compression_ratio": 1.812206572769953, "no_speech_prob": 0.5888912677764893}, {"id": 3, "seek": 0, "start": 14.0, "end": 18.0, "text": " because the curtains look a little wee bit, over the, over the window blind,", "tokens": [780, 262, 41160, 804, 257, 1310, 43671, 1643, 11, 625, 262, 11, 625, 262, 4324, 7770, 11], "temperature": 0.0, "avg_logprob": -0.36820535098805146, "compression_ratio": 1.812206572769953, "no_speech_prob": 0.5888912677764893}, {"id": 4, "seek": 0, "start": 18.0, "end": 21.0, "text": " but the window looks a little wee bit puffy.", "tokens": [475, 262, 4324, 3073, 257, 1310, 43671, 1643, 279, 15352, 13], "temperature": 0.0, "avg_logprob": -0.36820535098805146, "compression_ratio": 1.812206572769953, "no_speech_prob": 0.5888912677764893}, {"id": 5, "seek": 0, "start": 21.0, "end": 25.0, "text": " So maybe there's a slight breeze coming in the, in the kitchen window.", "tokens": [1406, 3863, 612, 338, 257, 3731, 28633, 2406, 287, 262, 11, 287, 262, 9592, 4324, 13], "temperature": 0.0, "avg_logprob": -0.36820535098805146, "compression_ratio": 1.812206572769953, "no_speech_prob": 0.5888912677764893}, {"id": 6, "seek": 2500, "start": 25.0, "end": 30.0, "text": " Mom is drying the dishes and she's forgetting herself, and the water is overflowing.", "tokens": [50363, 11254, 318, 29621, 262, 16759, 290, 673, 338, 32012, 5223, 11, 290, 262, 1660, 318, 43347, 13, 50613], "temperature": 0.0, "avg_logprob": -0.21775527000427247, "compression_ratio": 1.0769230769230769, "no_speech_prob": 8.530239028914366e-06}], "language": "en", "label": 1}