{"text": " Okay, see going on in the picture. Boys reach for the cookie jar, the stool is falling over. The girl is holding her hand up for cookies and then they go over in the picture. Mother, the water is overflowing from her sink. She's drying dishes. She's looking out a window. Water is on the floor.", "segments": [{"id": 0, "seek": 0, "start": 0.0, "end": 3.0, "text": " Okay, see going on in the picture.", "tokens": [16805, 11, 766, 1016, 319, 287, 262, 4286, 13], "temperature": 0.0, "avg_logprob": -0.3809249981029614, "compression_ratio": 1.6130952380952381, "no_speech_prob": 0.1301257163286209}, {"id": 1, "seek": 0, "start": 10.0, "end": 14.0, "text": " Boys reach for the cookie jar, the stool is falling over.", "tokens": [17528, 3151, 329, 262, 19751, 17379, 11, 262, 38753, 318, 7463, 625, 13], "temperature": 0.0, "avg_logprob": -0.3809249981029614, "compression_ratio": 1.6130952380952381, "no_speech_prob": 0.1301257163286209}, {"id": 2, "seek": 0, "start": 15.0, "end": 21.0, "text": " The girl is holding her hand up for cookies and then they go over in the picture.", "tokens": [383, 2576, 318, 4769, 607, 1021, 510, 329, 14746, 290, 788, 484, 467, 625, 287, 262, 4286, 13], "temperature": 0.0, "avg_logprob": -0.3809249981029614, "compression_ratio": 1.6130952380952381, "no_speech_prob": 0.1301257163286209}, {"id": 3, "seek": 0, "start": 21.0, "end": 24.0, "text": " Mother, the water is overflowing from her sink.", "tokens": [10584, 11, 262, 1660, 318, 43347, 422, 607, 14595, 13], "temperature": 0.0, "avg_logprob": -0.3809249981029614, "compression_ratio": 1.6130952380952381, "no_speech_prob": 0.1301257163286209}, {"id": 4, "seek": 0, "start": 24.0, "end": 27.0, "text": " She's drying dishes. She's looking out a window.", "tokens": [1375, 338, 29621, 16759, 13, 1375, 338, 2045, 503, 257, 4324, 13], "temperature": 0.0, "avg_logprob": -0.3809249981029614, "compression_ratio": 1.6130952380952381, "no_speech_prob": 0.1301257163286209}, {"id": 5, "seek": 2700, "start": 27.0, "end": 29.0, "text": " Water is on the floor.", "tokens": [50363, 5638, 318, 319, 262, 4314, 13, 50463], "temperature": 0.0, "avg_logprob": -0.14718451764848497, "compression_ratio": 0.7333333333333333, "no_speech_prob": 3.500827915559057e-06}], "language": "en", "label": 1}