{"text": " Here's the picture. Oh boy. Wow, the boy's going up on a cookie jar to get cookies and he's falling off the jar and his sister is just wondering about it. Will he hit the bottom? Norma has a sink that's over running with water splashing down onto her shoes. She's in the process of drying dishes. She's looking out an open window at the same time. Cookie jars all over.", "segments": [{"id": 0, "seek": 0, "start": 0.0, "end": 2.0, "text": " Here's the picture.", "tokens": [3423, 338, 262, 4286, 13], "temperature": 0.0, "avg_logprob": -0.23857220736416904, "compression_ratio": 1.5772727272727274, "no_speech_prob": 0.29602423310279846}, {"id": 1, "seek": 0, "start": 2.0, "end": 4.0, "text": " Oh boy.", "tokens": [3966, 2933, 13], "temperature": 0.0, "avg_logprob": -0.23857220736416904, "compression_ratio": 1.5772727272727274, "no_speech_prob": 0.29602423310279846}, {"id": 2, "seek": 0, "start": 4.0, "end": 12.0, "text": " Wow, the boy's going up on a cookie jar to get cookies and he's falling off the jar and his sister is just wondering about it.", "tokens": [24755, 11, 262, 2933, 338, 1016, 510, 319, 257, 19751, 17379, 284, 651, 14746, 290, 339, 338, 7463, 572, 262, 17379, 290, 465, 6621, 318, 655, 11263, 546, 340, 13], "temperature": 0.0, "avg_logprob": -0.23857220736416904, "compression_ratio": 1.5772727272727274, "no_speech_prob": 0.29602423310279846}, {"id": 3, "seek": 0, "start": 12.0, "end": 14.0, "text": " Will he hit the bottom?", "tokens": [2561, 339, 2277, 262, 4220, 30], "temperature": 0.0, "avg_logprob": -0.23857220736416904, "compression_ratio": 1.5772727272727274, "no_speech_prob": 0.29602423310279846}, {"id": 4, "seek": 0, "start": 14.0, "end": 21.0, "text": " Norma has a sink that's over running with water splashing down onto her shoes.", "tokens": [11220, 64, 468, 257, 14595, 326, 338, 625, 2491, 351, 1660, 4328, 2140, 866, 4291, 607, 10012, 13], "temperature": 0.0, "avg_logprob": -0.23857220736416904, "compression_ratio": 1.5772727272727274, "no_speech_prob": 0.29602423310279846}, {"id": 5, "seek": 0, "start": 21.0, "end": 24.0, "text": " She's in the process of drying dishes.", "tokens": [1375, 338, 287, 262, 1429, 286, 29621, 16759, 13], "temperature": 0.0, "avg_logprob": -0.23857220736416904, "compression_ratio": 1.5772727272727274, "no_speech_prob": 0.29602423310279846}, {"id": 6, "seek": 0, "start": 24.0, "end": 28.0, "text": " She's looking out an open window at the same time.", "tokens": [1375, 338, 2045, 503, 281, 1280, 4324, 379, 262, 976, 640, 13], "temperature": 0.0, "avg_logprob": -0.23857220736416904, "compression_ratio": 1.5772727272727274, "no_speech_prob": 0.29602423310279846}, {"id": 7, "seek": 2800, "start": 28.0, "end": 30.0, "text": " Cookie jars all over.", "tokens": [50363, 39606, 33008, 477, 625, 13, 50463], "temperature": 0.0, "avg_logprob": -0.6036280989646912, "compression_ratio": 0.7241379310344828, "no_speech_prob": 5.955108917987673e-06}], "language": "en", "label": 1}